{
  "date": "2024-01-17",
  "headline": "天气暖和了再叫醒我",
  "title": "巴伐利亚森林国家公园里睡觉的狼，德国",
  "description": "没有什么事情能比得上舒适的冬日小憩了。这只欧亚狼也同意这一点，它似乎在宁静的巴伐利亚森林国家公园中沉沉睡去，又或许只是因为知道自己是顶级捕猎者而感到心安。巴伐利亚森林国家公园成立于1970年，是德国第一个国家公园，拥有中欧最大的森林面积。大雷切尔、小雷切尔和小阿尔伯等山峦连绵起伏，对于希望漫步于挪威云杉林的徒步旅行者来说是一个不大不小的挑战。不过，公园里并不只有徒步旅行者，还有许多生物，包括猞猁、熊、侏儒猫头鹰和欧亚狼。这些狼在头狼的带领下组成了亲密无间的狼群，它们在西欧被猎杀了几十年，最近才经常出现在公园里。",
  "image_url": "https://cn.bing.com/th?id=OHR.SleepyWolf_ZH-CN9870873990_1920x1080.webp",
  "main_text": "巴伐利亚森林国家公园成立于1970年，是德国第一个国家公园。"
}