{
  "date": "2024-09-30",
  "headline": "随浮冰漂流",
  "title": "斯匹次卑尔根岛北部的海象群，斯瓦尔巴群岛，挪威",
  "description": "在午夜的阳光下，做什么事最爽？如果你是图片中的这只海象，那么答案可能是与你的同伴一起尽情畅泳，大口吃蛤蜊和贻贝，然后在海滩或浮冰上来个日光浴。欢迎来到斯瓦尔巴群岛，这是北冰洋中的一个群岛，在挪威和北极之间。这张照片拍摄于斯匹次卑尔根岛附近的海域，斯匹次卑尔根岛是该群岛九个岛屿中最大的一个，这些水生哺乳动物常年居住在这里，通常以雄性或雌性海象群的形式出现。雄性海象身长可达12英尺，体重超2600磅，在交配季节，它们会利用自己的体型相互争斗，争夺对雌性海象群的统治权，雌性海象群被称为胜者的“后宫”。",
  "image_url": "https://cn.bing.com/th?id=OHR.WalrusNorway_ZH-CN5657804031_1920x1080.webp",
  "main_text": "海象是一种鳍足类哺乳动物，和海豹以及海狮有着亲缘关系。它们最显著的特征是有着长长的獠牙，獠牙周围长着一层硬毛。"
}